petroleum/__init__.py
petroleum/conditional_task.py
petroleum/exceptions.py
petroleum/exclusive_choice.py
petroleum/json_encoder.py
petroleum/task.py
petroleum/task_log.py
petroleum/task_status.py
petroleum/workflow.py
petroleum/workflow_state.py
petroleum/workflow_status.py
petroleum-0.0.2.dist-info/LICENSE
petroleum-0.0.2.dist-info/METADATA
petroleum-0.0.2.dist-info/WHEEL
petroleum-0.0.2.dist-info/top_level.txt
petroleum-0.0.2.dist-info/RECORD
