Metadata-Version: 2.1
Name: petroleum
Version: 0.0.2
Summary: A pure workflow engine for Python
Home-page: https://github.com/bwind/petroleum
Author: Bas Wind
Author-email: mailtobwind+petroleum@gmail.com
License: UNKNOWN
Platform: UNKNOWN
Classifier: Programming Language :: Python :: 3 :: Only
Classifier: Development Status :: 3 - Alpha
Classifier: Intended Audience :: Developers
Classifier: License :: OSI Approved :: MIT License
Requires-Dist: dacite (==1.0.2)
